<?xml version="1.0" encoding="UTF-8"?>
<STLW10P10Batch xmlns="https://stlouis-mo.gov/" xmlns:xsi="http://www.w3.org/2001/XMLSchema-instance" xsi:schemaLocation="https://stlouis-mo.gov/ ../STLW10P10BatchType.xsd">
  <BatchHeader>
    <SubmitterName>Optiminal Corp</SubmitterName>
    <SubmitterAccountIdentifier>345439237</SubmitterAccountIdentifier>
    <SubmitterEmailAddress>submitter@optiminal.com</SubmitterEmailAddress>
    <TotalItems>25</TotalItems>
    <AmountDueTotal>17552.66</AmountDueTotal>
    <RemittanceTotal>17552.66</RemittanceTotal>
  </BatchHeader>
  <STLP10>
    <ReturnHeader>
      <AccountIdentifier>355668085</AccountIdentifier>
      <BusinessName>National Biotechnology</BusinessName>
      <Address>
        <USAddress>
          <StreetAddress1>1745 Smehrik Center</StreetAddress1>
          <City>Sydneyfort</City>
          <State>ND</State>
          <ZIPCode>64233</ZIPCode>
        </USAddress>
      </Address>
      <AddressChange/>
      <AmendedReturn/>
      <FinalReturn>false</FinalReturn>
    </ReturnHeader>
    <ReturnLiability>
      <FilingPeriod>2026-03-31</FilingPeriod>
      <TaxablePayroll>282656.27</TaxablePayroll>
      <GrossTaxDue>1413.28</GrossTaxDue>
      <PriorPayments>0</PriorPayments>
      <NetTaxDue>1413.28</NetTaxDue>
      <PenaltyDue>0</PenaltyDue>
      <InterestDue>0</InterestDue>
      <AmountDue>1413.28</AmountDue>
      <Remittance>1413.28</Remittance>
    </ReturnLiability>
  </STLP10>
  <STLP10>
    <ReturnHeader>
      <AccountIdentifier>039288799</AccountIdentifier>
      <BusinessName>Tarto LLC</BusinessName>
      <Address>
        <USAddress>
          <StreetAddress1>001 Earl Avenue</StreetAddress1>
          <City>West Angelinetown</City>
          <State>OH</State>
          <ZIPCode>56342</ZIPCode>
        </USAddress>
      </Address>
      <AddressChange/>
      <AmendedReturn/>
      <FinalReturn/>
    </ReturnHeader>
    <ReturnLiability>
      <FilingPeriod>2026-03-31</FilingPeriod>
      <TaxablePayroll>771.76</TaxablePayroll>
      <GrossTaxDue>3.86</GrossTaxDue>
      <PriorPayments>0</PriorPayments>
      <NetTaxDue>3.86</NetTaxDue>
      <PenaltyDue>0</PenaltyDue>
      <InterestDue>0</InterestDue>
      <AmountDue>3.86</AmountDue>
      <Remittance>3.86</Remittance>
    </ReturnLiability>
  </STLP10>
  <STLP10>
    <ReturnHeader>
      <AccountIdentifier>478947069</AccountIdentifier>
      <BusinessName>Molar Deli and Grocery and Sons</BusinessName>
      <Address>
        <USAddress>
          <StreetAddress1>847 Grant Boulevard</StreetAddress1>
          <City>West Staceyside</City>
          <State>NJ</State>
          <ZIPCode>75717</ZIPCode>
        </USAddress>
      </Address>
      <AddressChange>false</AddressChange>
      <AmendedReturn/>
      <FinalReturn/>
    </ReturnHeader>
    <ReturnLiability>
      <FilingPeriod>2026-03-31</FilingPeriod>
      <TaxablePayroll>97706.32</TaxablePayroll>
      <GrossTaxDue>488.53</GrossTaxDue>
      <PriorPayments>0</PriorPayments>
      <NetTaxDue>488.53</NetTaxDue>
      <PenaltyDue>0</PenaltyDue>
      <InterestDue>0</InterestDue>
      <AmountDue>488.53</AmountDue>
      <Remittance>488.53</Remittance>
    </ReturnLiability>
  </STLP10>
  <STLP10>
    <ReturnHeader>
      <AccountIdentifier>215834963</AccountIdentifier>
      <BusinessName>Chamgerlin Hazardous Waste Remediation</BusinessName>
      <Address>
        <USAddress>
          <StreetAddress1>68016 Laurianne Road</StreetAddress1>
          <City>Torphychester</City>
          <State>VT</State>
          <ZIPCode>84578-8129</ZIPCode>
        </USAddress>
      </Address>
      <AddressChange>true</AddressChange>
      <AmendedReturn/>
      <FinalReturn>true</FinalReturn>
    </ReturnHeader>
    <ReturnLiability>
      <FilingPeriod>2026-03-31</FilingPeriod>
      <TaxablePayroll>23507.3</TaxablePayroll>
      <GrossTaxDue>117.54</GrossTaxDue>
      <PriorPayments>0</PriorPayments>
      <NetTaxDue>117.54</NetTaxDue>
      <PenaltyDue>0</PenaltyDue>
      <InterestDue>0</InterestDue>
      <AmountDue>117.54</AmountDue>
      <Remittance>117.54</Remittance>
    </ReturnLiability>
  </STLP10>
  <STLP10>
    <ReturnHeader>
      <AccountIdentifier>202909336</AccountIdentifier>
      <BusinessName>Intercity</BusinessName>
      <Address>
        <USAddress>
          <StreetAddress1>0108 Lonzo Place</StreetAddress1>
          <City>Hegmannborough</City>
          <State>OK</State>
          <ZIPCode>18454</ZIPCode>
        </USAddress>
      </Address>
      <AddressChange/>
      <AmendedReturn/>
      <FinalReturn/>
    </ReturnHeader>
    <ReturnLiability>
      <FilingPeriod>2026-03-31</FilingPeriod>
      <TaxablePayroll>869458.03</TaxablePayroll>
      <GrossTaxDue>4347.29</GrossTaxDue>
      <PriorPayments>0</PriorPayments>
      <NetTaxDue>4347.29</NetTaxDue>
      <PenaltyDue>0</PenaltyDue>
      <InterestDue>0</InterestDue>
      <AmountDue>4347.29</AmountDue>
      <Remittance>4347.29</Remittance>
    </ReturnLiability>
  </STLP10>
  <STLP10>
    <ReturnHeader>
      <AccountIdentifier>752233226</AccountIdentifier>
      <BusinessName>United</BusinessName>
      <Address>
        <USAddress>
          <StreetAddress1>1355 Vargas Place</StreetAddress1>
          <City>Thielborough</City>
          <State>MI</State>
          <ZIPCode>37126</ZIPCode>
        </USAddress>
      </Address>
      <AddressChange/>
      <AmendedReturn/>
      <FinalReturn>false</FinalReturn>
    </ReturnHeader>
    <ReturnLiability>
      <FilingPeriod>2026-03-31</FilingPeriod>
      <TaxablePayroll>119587.45</TaxablePayroll>
      <GrossTaxDue>597.94</GrossTaxDue>
      <PriorPayments>0</PriorPayments>
      <NetTaxDue>597.94</NetTaxDue>
      <PenaltyDue>0</PenaltyDue>
      <InterestDue>0</InterestDue>
      <AmountDue>597.94</AmountDue>
      <Remittance>597.94</Remittance>
    </ReturnLiability>
  </STLP10>
  <STLP10>
    <ReturnHeader>
      <AccountIdentifier>910514241</AccountIdentifier>
      <BusinessName>Xtreme</BusinessName>
      <Address>
        <USAddress>
          <StreetAddress1>3112 Thora Square</StreetAddress1>
          <City>Eusebiochester</City>
          <State>LA</State>
          <ZIPCode>22926</ZIPCode>
        </USAddress>
      </Address>
      <AddressChange/>
      <AmendedReturn/>
      <FinalReturn/>
    </ReturnHeader>
    <ReturnLiability>
      <FilingPeriod>2026-03-31</FilingPeriod>
      <TaxablePayroll>63420.53</TaxablePayroll>
      <GrossTaxDue>317.1</GrossTaxDue>
      <PriorPayments>0</PriorPayments>
      <NetTaxDue>317.1</NetTaxDue>
      <PenaltyDue>0</PenaltyDue>
      <InterestDue>0</InterestDue>
      <AmountDue>317.1</AmountDue>
      <Remittance>317.1</Remittance>
    </ReturnLiability>
  </STLP10>
  <STLP10>
    <ReturnHeader>
      <AccountIdentifier>120887575</AccountIdentifier>
      <BusinessName>International Wood Products</BusinessName>
      <Address>
        <USAddress>
          <StreetAddress1>4829 Chadd Street</StreetAddress1>
          <City>West Samantaborough</City>
          <State>FL</State>
          <ZIPCode>26675-5870</ZIPCode>
        </USAddress>
      </Address>
      <AddressChange/>
      <AmendedReturn/>
      <FinalReturn/>
    </ReturnHeader>
    <ReturnLiability>
      <FilingPeriod>2026-03-31</FilingPeriod>
      <TaxablePayroll>38681.15</TaxablePayroll>
      <GrossTaxDue>193.41</GrossTaxDue>
      <PriorPayments>0</PriorPayments>
      <NetTaxDue>193.41</NetTaxDue>
      <PenaltyDue>0</PenaltyDue>
      <InterestDue>0</InterestDue>
      <AmountDue>193.41</AmountDue>
      <Remittance>193.41</Remittance>
    </ReturnLiability>
  </STLP10>
  <STLP10>
    <ReturnHeader>
      <AccountIdentifier>238959925</AccountIdentifier>
      <BusinessName>Reinger-Will</BusinessName>
      <Address>
        <USAddress>
          <StreetAddress1>516 Auer Boulevard</StreetAddress1>
          <City>North Emilieland</City>
          <State>Tennessee</State>
          <ZIPCode>65979</ZIPCode>
        </USAddress>
      </Address>
      <AddressChange/>
      <AmendedReturn/>
      <FinalReturn>false</FinalReturn>
    </ReturnHeader>
    <ReturnLiability>
      <FilingPeriod>2026-03-31</FilingPeriod>
      <TaxablePayroll>138025.31</TaxablePayroll>
      <GrossTaxDue>690.13</GrossTaxDue>
      <PriorPayments>0</PriorPayments>
      <NetTaxDue>690.13</NetTaxDue>
      <PenaltyDue>0</PenaltyDue>
      <InterestDue>0</InterestDue>
      <AmountDue>690.13</AmountDue>
      <Remittance>690.13</Remittance>
    </ReturnLiability>
  </STLP10>
  <STLP10>
    <ReturnHeader>
      <AccountIdentifier>954500258</AccountIdentifier>
      <BusinessName>IntelliBet</BusinessName>
      <Address>
        <USAddress>
          <StreetAddress1>88278 Block Street</StreetAddress1>
          <City>Keatonside</City>
          <State>VT</State>
          <ZIPCode>09669</ZIPCode>
        </USAddress>
      </Address>
      <AddressChange/>
      <AmendedReturn>true</AmendedReturn>
      <FinalReturn>FINAL</FinalReturn>
    </ReturnHeader>
    <ReturnLiability>
      <FilingPeriod>2026-03-31</FilingPeriod>
      <TaxablePayroll>678665.01</TaxablePayroll>
      <GrossTaxDue>3393.33</GrossTaxDue>
      <PriorPayments>0</PriorPayments>
      <NetTaxDue>3393.33</NetTaxDue>
      <PenaltyDue>0</PenaltyDue>
      <InterestDue>0</InterestDue>
      <AmountDue>3393.33</AmountDue>
      <Remittance>3393.33</Remittance>
    </ReturnLiability>
  </STLP10>
  <STLP10>
    <ReturnHeader>
      <AccountIdentifier>267077703</AccountIdentifier>
      <BusinessName>Oenaria Inc</BusinessName>
      <Address>
        <USAddress>
          <StreetAddress1>3932 Kuhn Boulevard</StreetAddress1>
          <City>Abshireshire</City>
          <State>MD</State>
          <ZIPCode>66572</ZIPCode>
        </USAddress>
      </Address>
      <AddressChange/>
      <AmendedReturn/>
      <FinalReturn/>
    </ReturnHeader>
    <ReturnLiability>
      <FilingPeriod>2026-03-31</FilingPeriod>
      <TaxablePayroll>90021.55</TaxablePayroll>
      <GrossTaxDue>450.11</GrossTaxDue>
      <PriorPayments>0</PriorPayments>
      <NetTaxDue>450.11</NetTaxDue>
      <PenaltyDue>0</PenaltyDue>
      <InterestDue>0</InterestDue>
      <AmountDue>450.11</AmountDue>
      <Remittance>450.11</Remittance>
    </ReturnLiability>
  </STLP10>
  <STLP10>
    <ReturnHeader>
      <AccountIdentifier>689501075</AccountIdentifier>
      <BusinessName>Fivnio Liquor and Beer</BusinessName>
      <Address>
        <USAddress>
          <StreetAddress1>8457 Lucienne Ford</StreetAddress1>
          <City>Lake Allison</City>
          <State>SC</State>
          <ZIPCode>32565</ZIPCode>
        </USAddress>
      </Address>
      <AddressChange/>
      <AmendedReturn/>
      <FinalReturn/>
    </ReturnHeader>
    <ReturnLiability>
      <FilingPeriod>2026-03-31</FilingPeriod>
      <TaxablePayroll>29589.67</TaxablePayroll>
      <GrossTaxDue>147.95</GrossTaxDue>
      <PriorPayments>0</PriorPayments>
      <NetTaxDue>147.95</NetTaxDue>
      <PenaltyDue>0</PenaltyDue>
      <InterestDue>0</InterestDue>
      <AmountDue>147.95</AmountDue>
      <Remittance>147.95</Remittance>
    </ReturnLiability>
  </STLP10>
  <STLP10>
    <ReturnHeader>
      <AccountIdentifier>547898674</AccountIdentifier>
      <BusinessName>Mindstar LLC</BusinessName>
      <Address>
        <USAddress>
          <StreetAddress1>335 Jennie Boulevard</StreetAddress1>
          <City>West Peyton</City>
          <State>RI</State>
          <ZIPCode>76074</ZIPCode>
        </USAddress>
      </Address>
      <AddressChange/>
      <AmendedReturn/>
      <FinalReturn/>
    </ReturnHeader>
    <ReturnLiability>
      <FilingPeriod>2026-03-31</FilingPeriod>
      <TaxablePayroll>111706.65</TaxablePayroll>
      <GrossTaxDue>558.53</GrossTaxDue>
      <PriorPayments>0</PriorPayments>
      <NetTaxDue>558.53</NetTaxDue>
      <PenaltyDue>0</PenaltyDue>
      <InterestDue>0</InterestDue>
      <AmountDue>558.53</AmountDue>
      <Remittance>558.53</Remittance>
    </ReturnLiability>
  </STLP10>
  <STLP10>
    <ReturnHeader>
      <AccountIdentifier>434191897</AccountIdentifier>
      <BusinessName>PixelForge LLC</BusinessName>
      <Address>
        <USAddress>
          <StreetAddress1>740 Joy Highway</StreetAddress1>
          <City>Port Kara</City>
          <State>MT</State>
          <ZIPCode>84201-1077</ZIPCode>
        </USAddress>
      </Address>
      <AddressChange>false</AddressChange>
      <AmendedReturn/>
      <FinalReturn/>
    </ReturnHeader>
    <ReturnLiability>
      <FilingPeriod>2026-03-31</FilingPeriod>
      <TaxablePayroll>12835.29</TaxablePayroll>
      <GrossTaxDue>64.18</GrossTaxDue>
      <PriorPayments>0</PriorPayments>
      <NetTaxDue>64.18</NetTaxDue>
      <PenaltyDue>0</PenaltyDue>
      <InterestDue>0</InterestDue>
      <AmountDue>64.18</AmountDue>
      <Remittance>64.18</Remittance>
    </ReturnLiability>
  </STLP10>
  <STLP10>
    <ReturnHeader>
      <AccountIdentifier>874814531</AccountIdentifier>
      <BusinessName>Weissnat Sealants Group</BusinessName>
      <Address>
        <USAddress>
          <StreetAddress1>05423 Lang Court</StreetAddress1>
          <City>East Dawsonview</City>
          <State>CT</State>
          <ZIPCode>49151-5522</ZIPCode>
        </USAddress>
      </Address>
      <AddressChange>true</AddressChange>
      <AmendedReturn/>
      <FinalReturn/>
    </ReturnHeader>
    <ReturnLiability>
      <FilingPeriod>2026-03-31</FilingPeriod>
      <TaxablePayroll>94569.39</TaxablePayroll>
      <GrossTaxDue>472.85</GrossTaxDue>
      <PriorPayments>0</PriorPayments>
      <NetTaxDue>472.85</NetTaxDue>
      <PenaltyDue>0</PenaltyDue>
      <InterestDue>0</InterestDue>
      <AmountDue>472.85</AmountDue>
      <Remittance>472.85</Remittance>
    </ReturnLiability>
  </STLP10>
  <STLP10>
    <ReturnHeader>
      <AccountIdentifier>317260888</AccountIdentifier>
      <BusinessName>Kutch-Littel</BusinessName>
      <Address>
        <USAddress>
          <StreetAddress1>096 Torp Causeway</StreetAddress1>
          <City>Alvaville</City>
          <State>IL</State>
          <ZIPCode>80358</ZIPCode>
        </USAddress>
      </Address>
      <AddressChange/>
      <AmendedReturn/>
      <FinalReturn/>
    </ReturnHeader>
    <ReturnLiability>
      <FilingPeriod>2026-03-31</FilingPeriod>
      <TaxablePayroll>15617.62</TaxablePayroll>
      <GrossTaxDue>78.09</GrossTaxDue>
      <PriorPayments>0</PriorPayments>
      <NetTaxDue>78.09</NetTaxDue>
      <PenaltyDue>0</PenaltyDue>
      <InterestDue>0</InterestDue>
      <AmountDue>78.09</AmountDue>
      <Remittance>78.09</Remittance>
    </ReturnLiability>
  </STLP10>
  <STLP10>
    <ReturnHeader>
      <AccountIdentifier>685351925</AccountIdentifier>
      <BusinessName>Frami-McKenzie Leather Repair and Sons</BusinessName>
      <Address>
        <USAddress>
          <StreetAddress1>75004 Bradtke Way</StreetAddress1>
          <City>Raquelfort</City>
          <State>DE</State>
          <ZIPCode>49128-1073</ZIPCode>
        </USAddress>
      </Address>
      <AddressChange/>
      <AmendedReturn/>
      <FinalReturn/>
    </ReturnHeader>
    <ReturnLiability>
      <FilingPeriod>2026-03-31</FilingPeriod>
      <TaxablePayroll>18453.7</TaxablePayroll>
      <GrossTaxDue>92.27</GrossTaxDue>
      <PriorPayments>0</PriorPayments>
      <NetTaxDue>92.27</NetTaxDue>
      <PenaltyDue>0</PenaltyDue>
      <InterestDue>0</InterestDue>
      <AmountDue>92.27</AmountDue>
      <Remittance>92.27</Remittance>
    </ReturnLiability>
  </STLP10>
  <STLP10>
    <ReturnHeader>
      <AccountIdentifier>311148989</AccountIdentifier>
      <BusinessName>Diminica Tire and Tube LLC</BusinessName>
      <Address>
        <USAddress>
          <StreetAddress1>01460 Jade Crossing</StreetAddress1>
          <City>Emanuelbury</City>
          <State>MS</State>
          <ZIPCode>22892</ZIPCode>
        </USAddress>
      </Address>
      <AddressChange>false</AddressChange>
      <AmendedReturn/>
      <FinalReturn/>
    </ReturnHeader>
    <ReturnLiability>
      <FilingPeriod>2026-03-31</FilingPeriod>
      <TaxablePayroll>55772.74</TaxablePayroll>
      <GrossTaxDue>278.86</GrossTaxDue>
      <PriorPayments>0</PriorPayments>
      <NetTaxDue>278.86</NetTaxDue>
      <PenaltyDue>0</PenaltyDue>
      <InterestDue>0</InterestDue>
      <AmountDue>278.86</AmountDue>
      <Remittance>278.86</Remittance>
    </ReturnLiability>
  </STLP10>
  <STLP10>
    <ReturnHeader>
      <AccountIdentifier>705251543</AccountIdentifier>
      <BusinessName>Premiere Elite Group</BusinessName>
      <Address>
        <USAddress>
          <StreetAddress1>7809 Osinski Plaza</StreetAddress1>
          <City>Port Minhborough</City>
          <State>MD</State>
          <ZIPCode>70947</ZIPCode>
        </USAddress>
      </Address>
      <AddressChange/>
      <AmendedReturn/>
      <FinalReturn/>
    </ReturnHeader>
    <ReturnLiability>
      <FilingPeriod>2026-03-31</FilingPeriod>
      <TaxablePayroll>101834.18</TaxablePayroll>
      <GrossTaxDue>509.17</GrossTaxDue>
      <PriorPayments>0</PriorPayments>
      <NetTaxDue>509.17</NetTaxDue>
      <PenaltyDue>0</PenaltyDue>
      <InterestDue>0</InterestDue>
      <AmountDue>509.17</AmountDue>
      <Remittance>509.17</Remittance>
    </ReturnLiability>
  </STLP10>
  <STLP10>
    <ReturnHeader>
      <AccountIdentifier>536548651</AccountIdentifier>
      <BusinessName>Radinity LLC</BusinessName>
      <Address>
        <USAddress>
          <StreetAddress1>1679 Emerald Street</StreetAddress1>
          <City>Emmitttown</City>
          <State>SC</State>
          <ZIPCode>10235</ZIPCode>
        </USAddress>
      </Address>
      <AddressChange/>
      <AmendedReturn/>
      <FinalReturn/>
    </ReturnHeader>
    <ReturnLiability>
      <FilingPeriod>2026-03-31</FilingPeriod>
      <TaxablePayroll>15309.42</TaxablePayroll>
      <GrossTaxDue>76.55</GrossTaxDue>
      <PriorPayments>0</PriorPayments>
      <NetTaxDue>76.55</NetTaxDue>
      <PenaltyDue>0</PenaltyDue>
      <InterestDue>0</InterestDue>
      <AmountDue>76.55</AmountDue>
      <Remittance>76.55</Remittance>
    </ReturnLiability>
  </STLP10>
  <STLP10>
    <ReturnHeader>
      <AccountIdentifier>818320201</AccountIdentifier>
      <BusinessName>Reichel Extermination</BusinessName>
      <Address>
        <USAddress>
          <StreetAddress1>8879 Rotoscope Estates</StreetAddress1>
          <City>Rodriguezton</City>
          <State>PA</State>
          <ZIPCode>86754-6402</ZIPCode>
        </USAddress>
      </Address>
      <AddressChange/>
      <AmendedReturn/>
      <FinalReturn/>
    </ReturnHeader>
    <ReturnLiability>
      <FilingPeriod>2026-03-31</FilingPeriod>
      <TaxablePayroll>310228.02</TaxablePayroll>
      <GrossTaxDue>1551.14</GrossTaxDue>
      <PriorPayments>0</PriorPayments>
      <NetTaxDue>1551.14</NetTaxDue>
      <PenaltyDue>0</PenaltyDue>
      <InterestDue>0</InterestDue>
      <AmountDue>1551.14</AmountDue>
      <Remittance>1551.14</Remittance>
    </ReturnLiability>
  </STLP10>
  <STLP10>
    <ReturnHeader>
      <AccountIdentifier>45-7857133</AccountIdentifier>
      <BusinessName>O'Crappenin-Strosin Bags and Boxes</BusinessName>
      <Address>
        <USAddress>
          <StreetAddress1>340 Davonte Center</StreetAddress1>
          <StreetAddress2>Suite 424</StreetAddress2>
          <City>Harveytown</City>
          <State>WV</State>
          <ZIPCode>46993</ZIPCode>
        </USAddress>
      </Address>
      <AddressChange>false</AddressChange>
      <AmendedReturn/>
      <FinalReturn/>
    </ReturnHeader>
    <ReturnLiability>
      <FilingPeriod>2026-03-31</FilingPeriod>
      <TaxablePayroll>106806.95</TaxablePayroll>
      <GrossTaxDue>534.03</GrossTaxDue>
      <PriorPayments>0</PriorPayments>
      <NetTaxDue>534.03</NetTaxDue>
      <PenaltyDue>0</PenaltyDue>
      <InterestDue>0</InterestDue>
      <AmountDue>534.03</AmountDue>
      <Remittance>534.03</Remittance>
    </ReturnLiability>
  </STLP10>
  <STLP10>
    <ReturnHeader>
      <AccountIdentifier>713711154</AccountIdentifier>
      <BusinessName>Herzog, Hettinger and Johns</BusinessName>
      <Address>
        <USAddress>
          <StreetAddress1>1118 Cheyenne Parkway</StreetAddress1>
          <City>Sidmouth</City>
          <State>MI</State>
          <ZIPCode>42441</ZIPCode>
        </USAddress>
      </Address>
      <AddressChange/>
      <AmendedReturn/>
      <FinalReturn/>
    </ReturnHeader>
    <ReturnLiability>
      <FilingPeriod>2026-03-31</FilingPeriod>
      <TaxablePayroll>31837.45</TaxablePayroll>
      <GrossTaxDue>159.19</GrossTaxDue>
      <PriorPayments>0</PriorPayments>
      <NetTaxDue>159.19</NetTaxDue>
      <PenaltyDue>0</PenaltyDue>
      <InterestDue>0</InterestDue>
      <AmountDue>159.19</AmountDue>
      <Remittance>159.19</Remittance>
    </ReturnLiability>
  </STLP10>
  <STLP10>
    <ReturnHeader>
      <AccountIdentifier>004699910</AccountIdentifier>
      <BusinessName>Macejkovic-Smorin Marketing</BusinessName>
      <Address>
        <USAddress>
          <StreetAddress1>1595 Roberta Avenue</StreetAddress1>
          <City>Hickleview</City>
          <State>IL</State>
          <ZIPCode>56851</ZIPCode>
        </USAddress>
      </Address>
      <AddressChange/>
      <AmendedReturn/>
      <FinalReturn/>
    </ReturnHeader>
    <ReturnLiability>
      <FilingPeriod>2026-03-31</FilingPeriod>
      <TaxablePayroll>183084.41</TaxablePayroll>
      <GrossTaxDue>915.42</GrossTaxDue>
      <PriorPayments>0</PriorPayments>
      <NetTaxDue>915.42</NetTaxDue>
      <PenaltyDue>0</PenaltyDue>
      <InterestDue>0</InterestDue>
      <AmountDue>915.42</AmountDue>
      <Remittance>915.42</Remittance>
    </ReturnLiability>
  </STLP10>
  <STLP10>
    <ReturnHeader>
      <AccountIdentifier>639260881</AccountIdentifier>
      <BusinessName>Monahan-Brakus</BusinessName>
      <Address>
        <USAddress>
          <StreetAddress1>76615 Kreiger Street</StreetAddress1>
          <City>West Jacksonmouth</City>
          <State>MO</State>
          <ZIPCode>71016-9057</ZIPCode>
        </USAddress>
      </Address>
      <AddressChange/>
      <AmendedReturn/>
      <FinalReturn/>
    </ReturnHeader>
    <ReturnLiability>
      <FilingPeriod>2026-03-31</FilingPeriod>
      <TaxablePayroll>20381.47</TaxablePayroll>
      <GrossTaxDue>101.91</GrossTaxDue>
      <PriorPayments>0</PriorPayments>
      <NetTaxDue>101.91</NetTaxDue>
      <PenaltyDue>0</PenaltyDue>
      <InterestDue>0</InterestDue>
      <AmountDue>101.91</AmountDue>
      <Remittance>101.91</Remittance>
    </ReturnLiability>
  </STLP10>
</STLW10P10Batch>
